{
  "date": "*",
  "per_year": 24,
  "payer": "Checking",
  "payee": "Savings",
  "title": "Dan's Paycheck",
  "buckets": [
  {
    "title": "Home Maintenance",
    "total": 262.50
  },
  {
    "title": "Home Improvement",
    "total": 60
  },
  {
    "title": "Oil",
    "total": 137.50
  },
  {
    "title": "AAA",
    "total": 5
  },
  {
    "title": "Pool Care",
    "total": 87.50
  },
  {
    "title": "Lawn Care",
    "total": 55
  },
  {
    "title": "Vacation",
    "total": 75
  },
  {
    "title": "Party",
    "total": 40
  },
  {
    "title": "Babysitter",
    "total": 0
  },
  {
    "title": "Kid Activities",
    "total": 145
  },
  {
    "title": "Magazines",
    "total": 5
  },
  {
    "title": "Car Insurance",
    "total": 142.5
  },
  {
    "title": "Car Maintenance",
    "total": 75
  },
  {
    "title": "Car Savings",
    "total": 0
  },
  {
    "title": "Clothes",
    "total": 200
  },
  {
    "title": "Dan Gifts",
    "total": 45
  },
  {
    "title": "Dan Swan's Taxes",
    "total": 15
  },
  {
    "title": "Dan Life Insurance",
    "total": 30
  },
  {
    "title": "Kathy Gifts",
    "total": 45
  },
  {
    "title": "Kathy Hair",
    "total": 0
  },
  {
    "title": "Kathy Wardrobe",
    "total": 0
  },
  {
    "title": "Kathy Life Insurance",
    "total": 12.5
  },
  {
    "title": "Slush",
    "total": 25
  },
  {
    "title": "Grammy",
    "total": 15
  },
  {
    "title": "Water",
    "total": 92.50
  },
  {
      "title": "Cash Flow",
      "total": -960.00
  }
  ]
}
